[{"id":1,"name":"zardasht update","age":24,"salary":"1500.00","gender":"male","hired_date":"2022-01-01 00:00:00","job_title":"manager","manager_id":null,"deleted":"0","created_at":"2022-02-20T18:51:40.000000Z","updated_at":"2022-02-20T19:05:58.000000Z"},{"id":2,"name":"ahmad","age":23,"salary":"800.00","gender":"male","hired_date":"2022-01-01 00:00:00","job_title":"employee","manager_id":1,"deleted":"0","created_at":"2022-02-20T19:10:44.000000Z","updated_at":"2022-02-20T19:10:44.000000Z"},{"id":3,"name":"muhammad","age":24,"salary":"800.00","gender":"male","hired_date":"2022-01-01 00:00:00","job_title":"employee","manager_id":1,"deleted":"0","created_at":"2022-02-20T19:38:53.000000Z","updated_at":"2022-02-20T19:38:53.000000Z"},{"id":4,"name":"ahmad najmadin","age":25,"salary":"800.00","gender":"male","hired_date":"2022-01-01 00:00:00","job_title":"employee","manager_id":1,"deleted":"0","created_at":"2022-02-20T19:39:49.000000Z","updated_at":"2022-02-20T19:39:49.000000Z"},{"id":5,"name":"ali","age":22,"salary":"800.00","gender":"male","hired_date":"2022-01-01 00:00:00","job_title":"employee","manager_id":1,"deleted":"0","created_at":"2022-02-20T19:51:43.000000Z","updated_at":"2022-02-20T19:51:43.000000Z"}]